bitmap/__init__.py
bitmap/bitmap.py
bitmap-0.0.7.dist-info/LICENSE.md
bitmap-0.0.7.dist-info/METADATA
bitmap-0.0.7.dist-info/WHEEL
bitmap-0.0.7.dist-info/top_level.txt
bitmap-0.0.7.dist-info/RECORD
