Metadata-Version: 2.1
Name: bitmap
Version: 0.0.7
Summary: .
Home-page: https://github.com/wanji/bitmap
Author: WAN Ji
Author-email: wanji@live.com
License: UNKNOWN
Platform: UNKNOWN
Classifier: Programming Language :: Python :: 2.7
Classifier: Programming Language :: Python :: 3.7
Requires-Dist: future
